{
  "Name": "YZB_PAKET",
  "Path": "C:\\Users\\PC_4232\\AppData\\Roaming\\PacketAnalysis\\Matched_YZB_Paket.cs",
  "Freq": {
    "YZB_SURECLER.SUREC_1": 4,
    "YZB_SURECLER.SUREC_2": 2,
    "YZB_SURECLER.SUREC_3": 3,
    "YZB_SURECLER.SUREC_4": 2,
    "YZB_SURECLER.SUREC_5": 4,
    "YZB_SISTEMLER.SISTEM_1": 2,
    "YZB_SISTEMLER.SISTEM_2": 2,
    "YZB_SISTEMLER.SISTEM_3": 2,
    "YZB_SISTEMLER.SISTEM_4": 2,
    "YZB_SISTEMLER.SISTEM_5": 2,
    "YZB_NAVIGASYON.NAVIGASYON_1": 2,
    "YZB_NAVIGASYON.NAVIGASYON_2": 2,
    "YZB_NAVIGASYON.NAVIGASYON_3": 2,
    "YZB_NAVIGASYON.NAVIGASYON_4": 2,
    "YZB_NAVIGASYON.NAVIGASYON_5": 2,
    "YZB_GPS.GPS_1": 2,
    "YZB_GPS.GPS_2": 2,
    "YZB_GPS.GPS_3": 2,
    "YZB_GPS.GPS_4": 2,
    "YZB_GPS.GPS_5": 2,
    "YZB_KONUM.KONUM_1": 2,
    "YZB_KONUM.KONUM_2": 2,
    "YZB_KONUM.KONUM_3": 2,
    "YZB_KONUM.KONUM_4": 2,
    "YZB_KONUM.KONUM_5": 2
  },
  "Dim": {
    "YZB_SURECLER.SUREC_1": 500,
    "YZB_SURECLER.SUREC_2": 400,
    "YZB_SURECLER.SUREC_3": 800,
    "YZB_SURECLER.SUREC_4": 600,
    "YZB_SURECLER.SUREC_5": 300,
    "YZB_SISTEMLER.SISTEM_1": 600,
    "YZB_SISTEMLER.SISTEM_2": 500,
    "YZB_SISTEMLER.SISTEM_3": 700,
    "YZB_SISTEMLER.SISTEM_4": 800,
    "YZB_SISTEMLER.SISTEM_5": 500,
    "YZB_NAVIGASYON.NAVIGASYON_1": 600,
    "YZB_NAVIGASYON.NAVIGASYON_2": 600,
    "YZB_NAVIGASYON.NAVIGASYON_3": 600,
    "YZB_NAVIGASYON.NAVIGASYON_4": 600,
    "YZB_NAVIGASYON.NAVIGASYON_5": 600,
    "YZB_GPS.GPS_1": 600,
    "YZB_GPS.GPS_2": 600,
    "YZB_GPS.GPS_3": 600,
    "YZB_GPS.GPS_4": 600,
    "YZB_GPS.GPS_5": 600,
    "YZB_KONUM.KONUM_1": 600,
    "YZB_KONUM.KONUM_2": 600,
    "YZB_KONUM.KONUM_3": 600,
    "YZB_KONUM.KONUM_4": 600,
    "YZB_KONUM.KONUM_5": 600
  }
}